tsknn/__init__.py
tsknn/tsknn.py
tsknn-0.1.0.dist-info/licenses/LICENSE
tsknn-0.1.0.dist-info/METADATA
tsknn-0.1.0.dist-info/WHEEL
tsknn-0.1.0.dist-info/top_level.txt
tsknn-0.1.0.dist-info/RECORD
