Metadata-Version: 2.4
Name: tsknn
Version: 0.1.0
Summary: tsknn is a Python implementation of the k-nearest neighbors (KNN) algorithm aimed at time series forecasting
Author: Ricardo Zago
License-Expression: MIT
Project-URL: homepage, https://github.com/ricardozago/tsknn
Project-URL: tracker, https://github.com/ricardozago/tsknn/issues
Requires-Python: >=3.8
License-File: LICENSE
Requires-Dist: numpy>=1.20
Provides-Extra: test
Requires-Dist: pytest>=7.0; extra == "test"
Requires-Dist: pytest-cov>=4.0; extra == "test"
Requires-Dist: numpy>=1.20; extra == "test"
Requires-Dist: pandas>=1.3.0; extra == "test"
Requires-Dist: rpy2>=3.4.0; extra == "test"
Dynamic: license-file
